showlog/__init__.py
showlog-0.0.6.dist-info/LICENSE
showlog-0.0.6.dist-info/METADATA
showlog-0.0.6.dist-info/WHEEL
showlog-0.0.6.dist-info/top_level.txt
showlog-0.0.6.dist-info/RECORD
