Metadata-Version: 2.1
Name: showlog
Version: 0.0.6
Summary: make it easy to use log
Home-page: https://gitee.com/ZeroSeeker/showlog
Author: ZeroSeeker
Author-email: zeroseeker@foxmail.com
License: UNKNOWN
Platform: UNKNOWN
Classifier: Programming Language :: Python :: 3
Classifier: License :: OSI Approved :: MIT License
Classifier: Operating System :: OS Independent
License-File: LICENSE
Requires-Dist: colorama (==0.4.4)
